{
  "version": "5",
  "dialect": "mysql",
  "entries": [
    {
      "idx": 0,
      "version": "5",
      "when": 1712317971225,
      "tag": "0000_same_prism",
      "breakpoints": true
    },
    {
      "idx": 1,
      "version": "5",
      "when": 1712397681848,
      "tag": "0001_cold_hiroim",
      "breakpoints": true
    },
    {
      "idx": 2,
      "version": "5",
      "when": 1712838755820,
      "tag": "0002_condemned_spot",
      "breakpoints": true
    },
    {
      "idx": 3,
      "version": "5",
      "when": 1713253515100,
      "tag": "0003_damp_callisto",
      "breakpoints": true
    },
    {
      "idx": 4,
      "version": "5",
      "when": 1713262413397,
      "tag": "0004_last_firedrake",
      "breakpoints": true
    },
    {
      "idx": 5,
      "version": "5",
      "when": 1713798774189,
      "tag": "0005_flowery_frog_thor",
      "breakpoints": true
    },
    {
      "idx": 6,
      "version": "5",
      "when": 1719913661310,
      "tag": "0006_sleep_karma",
      "breakpoints": true
    },
    {
      "idx": 7,
      "version": "5",
      "when": 1719914169414,
      "tag": "0007_spooky_roland_deschain",
      "breakpoints": true
    },
    {
      "idx": 8,
      "version": "5",
      "when": 1720542397118,
      "tag": "0008_sour_falcon",
      "breakpoints": true
    },
    {
      "idx": 9,
      "version": "5",
      "when": 1722079956302,
      "tag": "0009_dark_ultron",
      "breakpoints": true
    }
  ]
}